Lensi_CLI/__init__.py
Lensi_CLI/__main__.py
Lensi_CLI/_init__.py
Lensi_CLI/_main_.py
Lensi-0.1.3.dist-info/METADATA
Lensi-0.1.3.dist-info/WHEEL
Lensi-0.1.3.dist-info/entry_points.txt
Lensi-0.1.3.dist-info/top_level.txt
Lensi-0.1.3.dist-info/RECORD
