Metadata-Version: 2.1
Name: Lensi
Version: 0.1.3
Summary: Lensi, install apps from QQ 360 Hippo Scoop Winget Choco
Home-page: https://gitee.com/lensit/lensi_cli/
Author: Lensit
Author-email: 1570515219@qq.com
License: MIT License
Platform: UNKNOWN
Requires-Dist: bs4
Requires-Dist: fuzzywuzzy[speedup]
Requires-Dist: fire
Requires-Dist: requests
Requires-Dist: configparser
Requires-Dist: tqdm
Requires-Dist: winshell
Requires-Dist: xpinyin
